<?xml version='1.0' encoding='UTF-8'?>
<arggraph id="micro_b022" topic_id="keep_retirement_at_63" stance="con">
  <edu id="e1"><![CDATA[No, l'età pensionabile dovrebbe essere aumentata di nuovo a 65 anni.]]></edu>
  <edu id="e2"><![CDATA[Le persone invecchiano in media,]]></edu>
  <edu id="e3"><![CDATA[ma non sono più malate o più stupide per questo.]]></edu>
  <edu id="e4"><![CDATA[Senza di loro perderemmo molta esperienza accumulata.]]></edu>
  <edu id="e5"><![CDATA[Dovremmo anche offrire maggiori attività di svago agli anziani.]]></edu>
  <adu id="a1" type="pro"/>
  <adu id="a2" type="opp"/>
  <adu id="a3" type="pro"/>
  <adu id="a4" type="pro"/>
  <adu id="a5" type="pro"/>
  <edge id="c6" src="e1" trg="a1" type="seg"/>
  <edge id="c7" src="e2" trg="a2" type="seg"/>
  <edge id="c8" src="e3" trg="a3" type="seg"/>
  <edge id="c9" src="e4" trg="a4" type="seg"/>
  <edge id="c10" src="e5" trg="a5" type="seg"/>
  <edge id="c2" src="a2" trg="c3" type="und"/>
  <edge id="c3" src="a3" trg="a1" type="sup"/>
  <edge id="c4" src="a4" trg="a1" type="sup"/>
  <edge id="c5" src="a5" trg="a1" type="sup"/>
</arggraph>  